hello_robot_stretch_urdf-0.1.2.data/scripts/stretch_urdf_example.py
hello_robot_stretch_urdf-0.1.2.data/scripts/stretch_urdf_ros_update.py
hello_robot_stretch_urdf-0.1.2.data/scripts/stretch_urdf_viz.py
stretch_urdf/__init__.py
stretch_urdf/helpers.py
stretch_urdf/urdf_utils.py
stretch_urdf/RE1V0/stretch_description_RE1V0_tool_none.urdf
stretch_urdf/RE1V0/stretch_description_RE1V0_tool_stretch_dex_wrist.urdf
stretch_urdf/RE1V0/stretch_description_RE1V0_tool_stretch_gripper.urdf
stretch_urdf/RE1V0/meshes/base_imu.STL
stretch_urdf/RE1V0/meshes/base_imu_collision.STL
stretch_urdf/RE1V0/meshes/base_link.STL
stretch_urdf/RE1V0/meshes/base_link_collision.STL
stretch_urdf/RE1V0/meshes/d435.dae
stretch_urdf/RE1V0/meshes/laser.STL
stretch_urdf/RE1V0/meshes/laser_collision.STL
stretch_urdf/RE1V0/meshes/link_arm_l0.STL
stretch_urdf/RE1V0/meshes/link_arm_l0_collision.STL
stretch_urdf/RE1V0/meshes/link_arm_l1.STL
stretch_urdf/RE1V0/meshes/link_arm_l1_collision.STL
stretch_urdf/RE1V0/meshes/link_arm_l2.STL
stretch_urdf/RE1V0/meshes/link_arm_l2_collision.STL
stretch_urdf/RE1V0/meshes/link_arm_l3.STL
stretch_urdf/RE1V0/meshes/link_arm_l3_collision.STL
stretch_urdf/RE1V0/meshes/link_arm_l4.STL
stretch_urdf/RE1V0/meshes/link_arm_l4_collision.STL
stretch_urdf/RE1V0/meshes/link_aruco_inner_wrist.STL
stretch_urdf/RE1V0/meshes/link_aruco_inner_wrist_collision.STL
stretch_urdf/RE1V0/meshes/link_aruco_left_base.STL
stretch_urdf/RE1V0/meshes/link_aruco_left_base_collision.STL
stretch_urdf/RE1V0/meshes/link_aruco_right_base.STL
stretch_urdf/RE1V0/meshes/link_aruco_right_base_collision.STL
stretch_urdf/RE1V0/meshes/link_aruco_shoulder.STL
stretch_urdf/RE1V0/meshes/link_aruco_shoulder_collision.STL
stretch_urdf/RE1V0/meshes/link_aruco_top_wrist.STL
stretch_urdf/RE1V0/meshes/link_aruco_top_wrist_collision.STL
stretch_urdf/RE1V0/meshes/link_dry_erase_holder.STL
stretch_urdf/RE1V0/meshes/link_dry_erase_marker.STL
stretch_urdf/RE1V0/meshes/link_gripper.STL
hello_robot_stretch_urdf-0.1.2.dist-info/LICENSE.md
hello_robot_stretch_urdf-0.1.2.dist-info/METADATA
hello_robot_stretch_urdf-0.1.2.dist-info/WHEEL
hello_robot_stretch_urdf-0.1.2.dist-info/top_level.txt
hello_robot_stretch_urdf-0.1.2.dist-info/RECORD
