Metadata-Version: 2.1
Name: hello-robot-stretch-urdf
Version: 0.1.2
Summary: Stretch URDF
Home-page: https://github.com/hello-robot/stretch_urdf
Author: Hello Robot Inc.
Author-email: support@hello-robot.com
Classifier: Programming Language :: Python :: 3
Classifier: Operating System :: OS Independent
License-File: LICENSE.md
Requires-Dist: urchin
